src/formulon/__about__.py
src/formulon/__init__.py
src/formulon/classical_physics.py
src/formulon/errorhandler.py
formulon_physics-0.1.3.dist-info/METADATA
formulon_physics-0.1.3.dist-info/WHEEL
formulon_physics-0.1.3.dist-info/licenses/LICENSE
formulon_physics-0.1.3.dist-info/licenses/LICENSE.txt
formulon_physics-0.1.3.dist-info/RECORD
