Metadata-Version: 2.1
Name: formulon-physics
Version: 0.1.3
Summary: An open-source Python library offering classical physics formulas with automatic input validation and NumPy support.
Project-URL: Documentation, https://github.com/SRIKALEESWARAR-S/formulon#readme
Project-URL: Issues, https://github.com/SRIKALEESWARAR-S/formulon/issues
Project-URL: Source, https://github.com/SRIKALEESWARAR-S/formulon
Author-email: SRIKALEESWARAR-S <srikaleeswarar675@gmail.com>
License: MIT
License-File: LICENSE
License-File: LICENSE.txt
Keywords: education,formulas,numpy,physics,science
Classifier: Development Status :: 4 - Beta
Classifier: Intended Audience :: Education
Classifier: License :: OSI Approved :: MIT License
Classifier: Programming Language :: Python
Classifier: Programming Language :: Python :: 3
Classifier: Programming Language :: Python :: 3.8
Classifier: Programming Language :: Python :: 3.9
Classifier: Programming Language :: Python :: 3.10
Classifier: Programming Language :: Python :: 3.11
Classifier: Programming Language :: Python :: 3.12
Classifier: Programming Language :: Python :: Implementation :: CPython
Classifier: Programming Language :: Python :: Implementation :: PyPy
Requires-Python: >=3.8
Requires-Dist: numpy>=1.20
